unit_averaging/__init__.py
unit_averaging/averager.py
unit_averaging/focus_function.py
unit_averaging/py.typed
unit_averaging-1.0.0.dist-info/licenses/LICENSE
unit_averaging-1.0.0.dist-info/METADATA
unit_averaging-1.0.0.dist-info/WHEEL
unit_averaging-1.0.0.dist-info/top_level.txt
unit_averaging-1.0.0.dist-info/RECORD
