Metadata-Version: 2.4
Name: unit_averaging
Version: 1.0.0
Summary: Unit averaging in Python: efficient ensemble estimation of unit-specific parameters
Author: Vladislav Morozov
License-Expression: MIT
Project-URL: Homepage, https://github.com/vladislav-morozov/unit-averaging/
Project-URL: Documentation, https://vladislav-morozov.github.io/unit-averaging/
Keywords: ensemble
Classifier: Development Status :: 4 - Beta
Classifier: Intended Audience :: Science/Research
Classifier: Intended Audience :: Education
Classifier: Topic :: Scientific/Engineering
Classifier: Programming Language :: Python :: 3
Classifier: Programming Language :: Python :: 3.12
Classifier: Programming Language :: Python :: 3.13
Requires-Python: >=3.12
License-File: LICENSE
Requires-Dist: cvxpy>=1.0.0
Requires-Dist: numpy>=2.0.0
Dynamic: license-file
